jsonapy/__init__.py
jsonapy/base_resource.py
jsonapy/utils.py
jsonapy-0.1.1.dist-info/WHEEL
jsonapy-0.1.1.dist-info/METADATA
jsonapy-0.1.1.dist-info/RECORD
